gpt_do/__init__.py
gpt_do/cli.py
gpt_do/doers/__init__.py
gpt_do/doers/doer.py
gpt_do/doers/gpt3_doer.py
gpt_do/doers/pywright_doer.py
gpt_do/getch.py
gpt_do/vendor/chatgpt_wrapper/.git
gpt_do/vendor/chatgpt_wrapper/.gitignore
gpt_do/vendor/chatgpt_wrapper/License
gpt_do/vendor/chatgpt_wrapper/README.md
gpt_do/vendor/chatgpt_wrapper/__init__.py
gpt_do/vendor/chatgpt_wrapper/chatgpt_wrapper/__init__.py
gpt_do/vendor/chatgpt_wrapper/chatgpt_wrapper/chatgpt.py
gpt_do/vendor/chatgpt_wrapper/postinstall.sh
gpt_do/vendor/chatgpt_wrapper/requirements.txt
gpt_do/vendor/chatgpt_wrapper/setup.py
gpt_do-0.1.16.dist-info/WHEEL
gpt_do-0.1.16.dist-info/entry_points.txt
gpt_do-0.1.16.dist-info/METADATA
gpt_do-0.1.16.dist-info/RECORD
