Metadata-Version: 2.1
Name: gpt-do
Version: 0.1.16
Summary: GPT-powered bash commands.
Home-page: https://github.com/yasyf/gpt-do
License: MIT
Author: Yasyf Mohamedali
Author-email: yasyfm@gmail.com
Requires-Python: >=3.9.0,<4.0.0
Classifier: License :: OSI Approved :: MIT License
Classifier: Programming Language :: Python :: 3
Classifier: Programming Language :: Python :: 3.9
Classifier: Programming Language :: Python :: 3.10
Classifier: Programming Language :: Python :: 3.11
Requires-Dist: click (>=8.1.3,<9.0.0)
Requires-Dist: dirtyjson (>=1.0.8,<2.0.0)
Requires-Dist: openai (>=0.25.0,<0.26.0)
Requires-Dist: playwright (>=1.29.0,<2.0.0)
Requires-Dist: py-getch (>=1.0.1,<2.0.0)
Requires-Dist: retry (>=0.9.2,<0.10.0)
Requires-Dist: rich (>=12.6.0,<13.0.0)
Project-URL: Repository, https://github.com/yasyf/gpt-do
